exosim/__init__.py
exosim/data/Zodi_map.hdf5
exosim/exosim.py
exosim/log/__init__.py
exosim/log/logger.py
exosim/models/__init__.py
exosim/models/channel.py
exosim/models/signal.py
exosim/models/utils/__init__.py
exosim/models/utils/cachedData.py
exosim/output/__init__.py
exosim/output/hdf5/__init__.py
exosim/output/hdf5/hdf5.py
exosim/output/hdf5/utils.py
exosim/output/output.py
exosim/output/setOutput.py
exosim/output/utils.py
exosim/plots/__init__.py
exosim/plots/focalPlanePlotter.py
exosim/plots/ndrsPlotter.py
exosim/plots/plotter.py
exosim/plots/radiometricPlotter.py
exosim/plots/subExposuresPlotter.py
exosim/plots/utils.py
exosim/recipes/__init__.py
exosim/recipes/createFocalPlane.py
exosim/recipes/createNDRs.py
exosim/recipes/createSubExposures.py
exosim/recipes/radiometricModel.py
exosim/tasks/__init__.py
exosim/tasks/astrosignal/__init__.py
exosim/tasks/astrosignal/applyAstronomicalSignal.py
exosim/tasks/astrosignal/estimateAstronomicalSignal.py
exosim/tasks/astrosignal/estimatePlanetarySignal.py
exosim/tasks/astrosignal/findAstronomicalSignals.py
exosim/tasks/chainTask.py
exosim/tasks/detector/__init__.py
exosim/tasks/detector/accumulateSubExposures.py
exosim/tasks/detector/addConstantDarkCurrent.py
exosim/tasks/detector/addCosmicRays.py
exosim/tasks/detector/addDarkCurrentMapNumpy.py
exosim/tasks/detector/addGainDrift.py
exosim/tasks/detector/addKTC.py
exosim/tasks/detector/addReadNoise.py
exosim/tasks/detector/addReadNoiseMapNumpy.py
exosim/tasks/detector/addShotNoise.py
exosim/tasks/detector/analogToDigital.py
exosim/tasks/detector/applyDeadPixelMap.py
exosim/tasks/detector/applyDeadPixelMapNumpy.py
exosim/tasks/detector/applyPixelsNonLinearity.py
exosim/tasks/detector/applySimpleSaturation.py
exosim/tasks/detector/loadPixelsNonLinearityMap.py
exosim/tasks/detector/loadPixelsNonLinearityMapNumpy.py
exosim/tasks/detector/mergeGroups.py
exosim/tasks/foregrounds/__init__.py
exosim/tasks/foregrounds/estimateZodi.py
exosim/tasks/instrument/__init__.py
exosim-2.1.1.dist-info/LICENSE
exosim-2.1.1.dist-info/METADATA
exosim-2.1.1.dist-info/WHEEL
exosim-2.1.1.dist-info/entry_points.txt
exosim-2.1.1.dist-info/RECORD
