Metadata-Version: 2.3
Name: exosim
Version: 2.1.1
Summary: ExoSim 2 is the next generation of the Exoplanet Observation Simulator (ExoSim) tailored for spectro-photometric observations of transiting exoplanets from space, ground, and sub-orbital platforms. This software is a complete rewrite implemented in Python 3, embracing object-oriented design principles.
License: BSD-3-Clause
Keywords: exoplanets,simulation,astronomy
Author: L. V. Mugnai
Author-email: lorenzo.mugnai@uniroma1.it
Requires-Python: >=3.12,<4.0
Classifier: Development Status :: 5 - Production/Stable
Classifier: Environment :: Console
Classifier: Intended Audience :: Developers
Classifier: Intended Audience :: Science/Research
Classifier: License :: OSI Approved :: BSD License
Classifier: Operating System :: OS Independent
Classifier: Programming Language :: Python :: 3
Classifier: Programming Language :: Python :: 3.12
Classifier: Programming Language :: Python :: 3.13
Classifier: Topic :: Scientific/Engineering
Classifier: Topic :: Software Development :: Libraries
Requires-Dist: astropy (>=7.1.0,<8.0.0)
Requires-Dist: batman-package (>=2.5.3,<3.0.0)
Requires-Dist: decorator
Requires-Dist: h5py (>=3.11,<4.0)
Requires-Dist: joblib (>=1.4.2,<2.0.0)
Requires-Dist: matplotlib (>=3.7.5,<4.0.0)
Requires-Dist: mpmath
Requires-Dist: numba (>=0.61.0,<0.62.0)
Requires-Dist: numpy (>=2.0.0,<3.0.0)
Requires-Dist: photutils (>=2.2.0,<3.0.0)
Requires-Dist: pyyaml (>=6.0.1,<7.0.0)
Requires-Dist: requests
Requires-Dist: rich-click (>=1.8.5,<2.0.0)
Requires-Dist: scipy (>=1.9.3,<2.0.0)
Requires-Dist: tqdm
Project-URL: Documentation, https://exosim2-public.readthedocs.io/en/latest/
Project-URL: Homepage, https://github.com/arielmission-space/ExoSim2-public
Project-URL: Repository, https://github.com/arielmission-space/ExoSim2-public
